.bumpversion.cfg
Dockerfile
MANIFEST.in
README.md
log
setup.py
yadage_state.json
yadage_workflow_instance.dot
yadage_workflow_instance.pdf
yadage_httpctrl_server.egg-info/PKG-INFO
yadage_httpctrl_server.egg-info/SOURCES.txt
yadage_httpctrl_server.egg-info/dependency_links.txt
yadage_httpctrl_server.egg-info/entry_points.txt
yadage_httpctrl_server.egg-info/requires.txt
yadage_httpctrl_server.egg-info/top_level.txt
yadagehttpctrl/__init__.py
yadagehttpctrl/clientcontroller.py
yadagehttpctrl/yadageblueprint.py
yadagehttpctrl/yadagehttpserver.py
yadagehttpctrl/static/ui.html
yadagehttpctrl/static/bower_components/cytoscape/.babelrc
yadagehttpctrl/static/bower_components/cytoscape/.bower.json
yadagehttpctrl/static/bower_components/cytoscape/.eslintrc.json
yadagehttpctrl/static/bower_components/cytoscape/.gitignore
yadagehttpctrl/static/bower_components/cytoscape/.npmignore
yadagehttpctrl/static/bower_components/cytoscape/.travis.yml
yadagehttpctrl/static/bower_components/cytoscape/ISSUE_TEMPLATE.md
yadagehttpctrl/static/bower_components/cytoscape/LICENSE
yadagehttpctrl/static/bower_components/cytoscape/README.md
yadagehttpctrl/static/bower_components/cytoscape/bower.json
yadagehttpctrl/static/bower_components/cytoscape/webpack.config.js
yadagehttpctrl/static/bower_components/cytoscape-dagre/.bower.json
yadagehttpctrl/static/bower_components/cytoscape-dagre/LICENSE
yadagehttpctrl/static/bower_components/cytoscape-dagre/README.md
yadagehttpctrl/static/bower_components/cytoscape-dagre/bower.json
yadagehttpctrl/static/bower_components/cytoscape-dagre/cytoscape-dagre.js
yadagehttpctrl/static/bower_components/cytoscape-dagre/demo.html
yadagehttpctrl/static/bower_components/cytoscape-dagre/gulpfile.js
yadagehttpctrl/static/bower_components/cytoscape-dagre/package.json
yadagehttpctrl/static/bower_components/cytoscape-expand-collapse/.bower.json
yadagehttpctrl/static/bower_components/cytoscape-expand-collapse/LICENSE.md
yadagehttpctrl/static/bower_components/cytoscape-expand-collapse/README.md
yadagehttpctrl/static/bower_components/cytoscape-expand-collapse/bower.json
yadagehttpctrl/static/bower_components/cytoscape-expand-collapse/cytoscape-expand-collapse.js
yadagehttpctrl/static/bower_components/cytoscape-expand-collapse/demo-undoable.html
