Metadata-Version: 1.0
Name: yadage-httpctrl-server
Version: 0.0.6
Summary: yadage http controller interfacint to persistent yadage controller
Home-page: UNKNOWN
Author: Lukas Heinrich
Author-email: lukas.heinrich@cern.ch
License: UNKNOWN
Platform: UNKNOWN
